{
   "max_cycles":17000,
   "total_cycles":-1,
   "measure_cycles":10000,
   "throughput":0.274612,
   "num_packets_transmitted":44910,
   "num_packets_received":43938,
   "average_packet_delay":21.0964,
   "max_packet_delay":11075,
   "packet.throughput":0.274612,
   "packet.num_packets_transmitted":44910,
   "packet.num_packets_received":43938,
   "packet.average_packet_delay":21.0964,
   "packet.max_packet_delay":11075,
   "acopacket.throughput":0,
   "acopacket.num_packets_transmitted":0,
   "acopacket.num_packets_received":0,
   "acopacket.average_packet_delay":0,
   "acopacket.max_packet_delay":0
}
