{
   "max_cycles":20000,
   "total_cycles":2524,
   "measure_cycles":1858,
   "throughput":0.336316,
   "num_packets_transmitted":10004,
   "num_packets_received":9998,
   "average_packet_delay":52.0693,
   "max_packet_delay":2091,
   "packet.throughput":0.336316,
   "packet.num_packets_transmitted":10004,
   "packet.num_packets_received":9998,
   "packet.average_packet_delay":52.0693,
   "packet.max_packet_delay":2091,
   "acopacket.throughput":0,
   "acopacket.num_packets_transmitted":0,
   "acopacket.num_packets_received":0,
   "acopacket.average_packet_delay":1e+07,
   "acopacket.max_packet_delay":162
}
